<annotation>
  <folder>3</folder>
  <filename>3_Choose-Your-Items-Wisely-Minimalist-Living-Room-Design.jpg</filename>
  <source>
    <database>Unknown</database>
    <annotation>Unknown</annotation>
    <image>Unknown</image>
  </source>
  <size>
    <width>1500</width>
    <height>844</height>
    <depth></depth>
  </size>
  <segmented>0</segmented>
  <object>
    <name>table</name>
    <truncated>0</truncated>
    <occluded>0</occluded>
    <difficult>0</difficult>
    <bndbox>
      <xmin>483.39</xmin>
      <ymin>616.58</ymin>
      <xmax>799.45</xmax>
      <ymax>833.66</ymax>
    </bndbox>
    <attributes>
      <attribute>
        <name>rotation</name>
        <value>0.0</value>
      </attribute>
    </attributes>
  </object>
  <object>
    <name>sofa</name>
    <truncated>0</truncated>
    <occluded>0</occluded>
    <difficult>0</difficult>
    <bndbox>
      <xmin>38.81</xmin>
      <ymin>480.26</ymin>
      <xmax>957.48</xmax>
      <ymax>838.0</ymax>
    </bndbox>
    <attributes>
      <attribute>
        <name>rotation</name>
        <value>0.0</value>
      </attribute>
    </attributes>
  </object>
  <object>
    <name>wall art</name>
    <truncated>0</truncated>
    <occluded>0</occluded>
    <difficult>0</difficult>
    <bndbox>
      <xmin>1020.0</xmin>
      <ymin>301.39</ymin>
      <xmax>1132.88</xmax>
      <ymax>436.84</ymax>
    </bndbox>
    <attributes>
      <attribute>
        <name>rotation</name>
        <value>0.0</value>
      </attribute>
    </attributes>
  </object>
  <object>
    <name>wall art</name>
    <truncated>0</truncated>
    <occluded>0</occluded>
    <difficult>0</difficult>
    <bndbox>
      <xmin>271.52</xmin>
      <ymin>287.49</ymin>
      <xmax>373.98</xmax>
      <ymax>433.37</ymax>
    </bndbox>
    <attributes>
      <attribute>
        <name>rotation</name>
        <value>0.0</value>
      </attribute>
    </attributes>
  </object>
  <object>
    <name>floor lamp</name>
    <truncated>0</truncated>
    <occluded>0</occluded>
    <difficult>0</difficult>
    <bndbox>
      <xmin>370.5</xmin>
      <ymin>257.1</ymin>
      <xmax>474.7</xmax>
      <ymax>496.76</ymax>
    </bndbox>
    <attributes>
      <attribute>
        <name>rotation</name>
        <value>0.0</value>
      </attribute>
    </attributes>
  </object>
  <object>
    <name>side table</name>
    <truncated>0</truncated>
    <occluded>0</occluded>
    <difficult>0</difficult>
    <bndbox>
      <xmin>302.78</xmin>
      <ymin>609.64</ymin>
      <xmax>398.29</xmax>
      <ymax>793.72</ymax>
    </bndbox>
    <attributes>
      <attribute>
        <name>rotation</name>
        <value>0.0</value>
      </attribute>
    </attributes>
  </object>
  <object>
    <name>side table</name>
    <truncated>0</truncated>
    <occluded>0</occluded>
    <difficult>0</difficult>
    <bndbox>
      <xmin>936.64</xmin>
      <ymin>561.01</ymin>
      <xmax>1044.3</xmax>
      <ymax>732.94</ymax>
    </bndbox>
    <attributes>
      <attribute>
        <name>rotation</name>
        <value>0.0</value>
      </attribute>
    </attributes>
  </object>
  <object>
    <name>large plant</name>
    <truncated>0</truncated>
    <occluded>0</occluded>
    <difficult>0</difficult>
    <bndbox>
      <xmin>1156.67</xmin>
      <ymin>354.35</ymin>
      <xmax>1351.18</xmax>
      <ymax>691.26</ymax>
    </bndbox>
    <attributes>
      <attribute>
        <name>rotation</name>
        <value>0.0</value>
      </attribute>
    </attributes>
  </object>
</annotation>
